{
  "title": "5 Stretching Secrets for a Flexible Body",
  "segments": [
    {
      "text": "Want to feel better? Stretching is the key!",
      "keywords": "person stretching"
    },
    {
      "text": "Most people skip stretching after workouts.",
      "keywords": "gym workout"
    },
    {
      "text": "Even 5 minutes of stretching can make a difference.",
      "keywords": "clock showing five minutes"
    },
    {
      "text": "Focus on major muscle groups for best results.",
      "keywords": "stretching muscles"
    },
    {
      "text": "Consistency is essential for lasting flexibility.",
      "keywords": "consistent person"
    },
    {
      "text": "Want to feel better? Stretching is the key!",
      "keywords": "person stretching"
    },
    {
      "text": "Follow for daily tips your body will thank you for.",
      "keywords": "person smiling"
    }
  ],
  "description": "Enhance your flexibility with easy stretching tips! Follow for daily health tips!",
  "hashtags": [
    "#health",
    "#wellness",
    "#stretching",
    "#healthtips",
    "#shorts",
    "#fyp",
    "#selfcare"
  ]
}